clipy/__init__.py
clipy/bflike.py
clipy/cmbonly.py
clipy/gibbs.py
clipy/lkl.py
clipy/minicldf.py
clipy/miniparse.py
clipy/reorg.py
clipy/simall.py
clipy/smica.py
clipy/smica_component.py
clipy/tools/clipy_change_data.py
clipy/tools/clipy_example_py.py
clipy/tools/clipy_print.py
clipy_like-0.15.dist-info/entry_points.txt
clipy_like-0.15.dist-info/licenses/LICENSE
clipy_like-0.15.dist-info/WHEEL
clipy_like-0.15.dist-info/METADATA
clipy_like-0.15.dist-info/RECORD
