Metadata-Version: 2.4
Name: clipy-like
Version: 0.15
Summary: Pure python clik implementation with jax support and candl integration.
Author-email: "K. Benabed" <benabed@iap.fr>, "L. Balkenhol" <lennart.balkenhol@iap.fr>
Requires-Python: >=3.9
Classifier: Programming Language :: Python :: 3
Classifier: Operating System :: OS Independent
License-File: LICENSE
Requires-Dist: numpy >= 1.23.5
Requires-Dist: astropy >= 2.0
Project-URL: Source, https://github.com/benabed/clipy
